{
  "mission_id": "CLUSTER",
  "dataset_count": 259,
  "generated_at": "2026-02-19T10:20:14Z",
  "datasets": [
    {
      "id": "C1_CP_CIS-CODIF_H1_1D_PEF",
      "description": "",
      "start_date": "2001-01-11",
      "stop_date": "2004-10-25",
      "parameter_count": 7,
      "instrument": ""
    },
    {
      "id": "C1_CP_CIS-CODIF_HE1_1D_PEF",
      "description": "",
      "start_date": "2001-01-11",
      "stop_date": "2004-10-25",
      "parameter_count": 7,
      "instrument": ""
    },
    {
      "id": "C1_CP_CIS-CODIF_HS_H1_PEF",
      "description": "",
      "start_date": "2001-01-11",
      "stop_date": "2004-10-25",
      "parameter_count": 6,
      "instrument": ""
    },
    {
      "id": "C1_CP_CIS-CODIF_HS_H1_PF",
      "description": "",
      "start_date": "2001-01-11",
      "stop_date": "2004-10-25",
      "parameter_count": 6,
      "instrument": ""
    },
    {
      "id": "C1_CP_CIS-CODIF_HS_H1_PSD",
      "description": "",
      "start_date": "2001-01-11",
      "stop_date": "2004-10-25",
      "parameter_count": 6,
      "instrument": ""
    },
    {
      "id": "C1_CP_CIS-CODIF_HS_HE1_PF",
      "description": "",
      "start_date": "2001-01-11",
      "stop_date": "2004-10-25",
      "parameter_count": 6,
      "instrument": ""
    },
    {
      "id": "C1_CP_CIS-CODIF_HS_HE1_PSD",
      "description": "",
      "start_date": "2001-01-11",
      "stop_date": "2004-10-25",
      "parameter_count": 6,
      "instrument": ""
    },
    {
      "id": "C1_CP_CIS-CODIF_HS_O1_PEF",
      "description": "",
      "start_date": "2001-01-11",
      "stop_date": "2004-10-25",
      "parameter_count": 6,
      "instrument": ""
    },
    {
      "id": "C1_CP_CIS-CODIF_HS_O1_PF",
      "description": "",
      "start_date": "2001-01-11",
      "stop_date": "2004-10-25",
      "parameter_count": 6,
      "instrument": ""
    },
    {
      "id": "C1_CP_CIS-CODIF_HS_O1_PSD",
      "description": "",
      "start_date": "2001-01-11",
      "stop_date": "2004-10-25",
      "parameter_count": 6,
      "instrument": ""
    },
    {
      "id": "C1_CP_CIS-CODIF_O1_1D_PEF",
      "description": "",
      "start_date": "2001-01-11",
      "stop_date": "2001-01-26",
      "parameter_count": 7,
      "instrument": ""
    },
    {
      "id": "C1_CP_CIS-CODIF_PAD_HS_H1_PF",
      "description": "",
      "start_date": "2001-01-31",
      "stop_date": "2004-10-25",
      "parameter_count": 4,
      "instrument": ""
    },
    {
      "id": "C1_CP_CIS-CODIF_PAD_HS_HE1_PF",
      "description": "",
      "start_date": "2001-01-31",
      "stop_date": "2004-10-25",
      "parameter_count": 4,
      "instrument": ""
    },
    {
      "id": "C1_CP_CIS-CODIF_PAD_HS_O1_PF",
      "description": "",
      "start_date": "2001-01-31",
      "stop_date": "2004-10-25",
      "parameter_count": 4,
      "instrument": ""
    },
    {
      "id": "C1_CP_CIS-HIA_HS_1D_PEF",
      "description": "",
      "start_date": "2001-01-10",
      "stop_date": "2020-06-16",
      "parameter_count": 7,
      "instrument": ""
    },
    {
      "id": "C1_CP_CIS-HIA_HS_MAG_IONS_PEF",
      "description": "",
      "start_date": "2001-01-11",
      "stop_date": "2020-06-16",
      "parameter_count": 6,
      "instrument": ""
    },
    {
      "id": "C1_CP_CIS-HIA_HS_MAG_IONS_PF",
      "description": "",
      "start_date": "2001-01-11",
      "stop_date": "2020-06-16",
      "parameter_count": 6,
      "instrument": ""
    },
    {
      "id": "C1_CP_CIS-HIA_HS_MAG_IONS_PSD",
      "description": "",
      "start_date": "2001-01-11",
      "stop_date": "2020-06-16",
      "parameter_count": 6,
      "instrument": ""
    },
    {
      "id": "C1_CP_CIS-HIA_HS_SW_IONS_PEF",
      "description": "",
      "start_date": "2001-01-10",
      "stop_date": "2011-03-24",
      "parameter_count": 6,
      "instrument": ""
    },
    {
      "id": "C1_CP_CIS-HIA_HS_SW_IONS_PF",
      "description": "",
      "start_date": "2001-01-10",
      "stop_date": "2011-03-24",
      "parameter_count": 6,
      "instrument": ""
    },
    {
      "id": "C1_CP_CIS-HIA_HS_SW_IONS_PSD",
      "description": "",
      "start_date": "2001-01-10",
      "stop_date": "2011-03-24",
      "parameter_count": 6,
      "instrument": ""
    },
    {
      "id": "C1_CP_CIS-HIA_LS_1D_PEF",
      "description": "",
      "start_date": "2001-01-10",
      "stop_date": "2011-03-24",
      "parameter_count": 7,
      "instrument": ""
    },
    {
      "id": "C1_CP_CIS-HIA_LS_SW_IONS_PEF",
      "description": "",
      "start_date": "2001-01-10",
      "stop_date": "2011-03-24",
      "parameter_count": 6,
      "instrument": ""
    },
    {
      "id": "C1_CP_CIS-HIA_LS_SW_IONS_PF",
      "description": "",
      "start_date": "2001-01-10",
      "stop_date": "2011-03-24",
      "parameter_count": 6,
      "instrument": ""
    },
    {
      "id": "C1_CP_CIS-HIA_LS_SW_IONS_PSD",
      "description": "",
      "start_date": "2001-01-10",
      "stop_date": "2011-03-24",
      "parameter_count": 6,
      "instrument": ""
    },
    {
      "id": "C1_CP_CIS-HIA_PAD_HS_MAG_IONS_PF",
      "description": "",
      "start_date": "2001-01-31",
      "stop_date": "2020-06-16",
      "parameter_count": 4,
      "instrument": ""
    },
    {
      "id": "C1_CP_EDI_AEDC",
      "description": "",
      "start_date": "2004-10-14",
      "stop_date": "2024-09-30",
      "parameter_count": 7,
      "instrument": ""
    },
    {
      "id": "C1_CP_EDI_MP",
      "description": "",
      "start_date": "2001-02-02",
      "stop_date": "2010-01-24",
      "parameter_count": 2,
      "instrument": ""
    },
    {
      "id": "C1_CP_EDI_QZC",
      "description": "",
      "start_date": "2001-02-02",
      "stop_date": "2024-09-12",
      "parameter_count": 2,
      "instrument": ""
    },
    {
      "id": "C1_CP_EDI_SPIN",
      "description": "",
      "start_date": "2001-02-02",
      "stop_date": "2024-09-12",
      "parameter_count": 2,
      "instrument": ""
    },
    {
      "id": "C1_CP_EFW_L3_E3D_INERT",
      "description": "",
      "start_date": "2000-12-05",
      "stop_date": "2018-12-10",
      "parameter_count": 3,
      "instrument": ""
    },
    {
      "id": "C1_CP_EFW_L3_P",
      "description": "",
      "start_date": "2000-12-05",
      "stop_date": "2024-09-30",
      "parameter_count": 1,
      "instrument": ""
    },
    {
      "id": "C1_CP_EFW_L3_V3D_INERT",
      "description": "",
      "start_date": "2000-12-05",
      "stop_date": "2018-12-10",
      "parameter_count": 3,
      "instrument": ""
    },
    {
      "id": "C1_CP_FGM_5VPS",
      "description": "",
      "start_date": "2000-12-03",
      "stop_date": "2024-09-29",
      "parameter_count": 3,
      "instrument": ""
    },
    {
      "id": "C1_CP_FGM_SPIN",
      "description": "",
      "start_date": "2001-01-30",
      "stop_date": "2024-09-29",
      "parameter_count": 3,
      "instrument": ""
    },
    {
      "id": "C1_CP_RAP_E3DD",
      "description": "",
      "start_date": "2000-12-01",
      "stop_date": "2023-09-18",
      "parameter_count": 2,
      "instrument": ""
    },
    {
      "id": "C1_CP_RAP_ESPCT6",
      "description": "",
      "start_date": "2000-12-01",
      "stop_date": "2023-09-18",
      "parameter_count": 2,
      "instrument": ""
    },
    {
      "id": "C1_CP_RAP_HSPCT",
      "description": "",
      "start_date": "2000-12-03",
      "stop_date": "2007-03-14",
      "parameter_count": 2,
      "instrument": ""
    },
    {
      "id": "C1_CP_RAP_I3DM_CNO",
      "description": "",
      "start_date": "2000-12-03",
      "stop_date": "2007-03-14",
      "parameter_count": 2,
      "instrument": ""
    },
    {
      "id": "C1_CP_RAP_I3DM_H",
      "description": "",
      "start_date": "2000-12-03",
      "stop_date": "2007-03-14",
      "parameter_count": 2,
      "instrument": ""
    },
    {
      "id": "C1_CP_RAP_I3DM_HE",
      "description": "",
      "start_date": "2000-12-03",
      "stop_date": "2007-03-14",
      "parameter_count": 2,
      "instrument": ""
    },
    {
      "id": "C1_CP_RAP_ISPCT_CNO",
      "description": "",
      "start_date": "2000-12-03",
      "stop_date": "2007-03-14",
      "parameter_count": 2,
      "instrument": ""
    },
    {
      "id": "C1_CP_RAP_ISPCT_HE",
      "description": "",
      "start_date": "2000-12-03",
      "stop_date": "2007-03-14",
      "parameter_count": 2,
      "instrument": ""
    },
    {
      "id": "C1_CP_RAP_L3DD",
      "description": "",
      "start_date": "2004-04-20",
      "stop_date": "2023-09-18",
      "parameter_count": 2,
      "instrument": ""
    },
    {
      "id": "C1_CP_RAP_PAD_CNO",
      "description": "",
      "start_date": "2000-12-03",
      "stop_date": "2007-03-15",
      "parameter_count": 3,
      "instrument": ""
    },
    {
      "id": "C1_CP_RAP_PAD_E3DD",
      "description": "",
      "start_date": "2000-12-03",
      "stop_date": "2023-09-18",
      "parameter_count": 3,
      "instrument": ""
    },
    {
      "id": "C1_CP_RAP_PAD_H",
      "description": "",
      "start_date": "2000-12-03",
      "stop_date": "2007-03-15",
      "parameter_count": 3,
      "instrument": ""
    },
    {
      "id": "C1_CP_RAP_PAD_HE",
      "description": "",
      "start_date": "2000-12-03",
      "stop_date": "2007-03-15",
      "parameter_count": 3,
      "instrument": ""
    },
    {
      "id": "C1_CP_RAP_PAD_L3DD",
      "description": "",
      "start_date": "2004-04-20",
      "stop_date": "2023-09-18",
      "parameter_count": 3,
      "instrument": ""
    },
    {
      "id": "C1_CP_STA_CWF_GSE",
      "description": "",
      "start_date": "2000-09-08",
      "stop_date": "2024-09-30",
      "parameter_count": 1,
      "instrument": ""
    },
    {
      "id": "C1_CP_STA_PPP",
      "description": "",
      "start_date": "2000-12-03",
      "stop_date": "2024-09-29",
      "parameter_count": 7,
      "instrument": ""
    },
    {
      "id": "C1_CP_STA_PSD",
      "description": "",
      "start_date": "2000-09-08",
      "stop_date": "2024-09-30",
      "parameter_count": 2,
      "instrument": ""
    },
    {
      "id": "C1_CP_STA_SM",
      "description": "",
      "start_date": "2000-09-08",
      "stop_date": "2024-09-30",
      "parameter_count": 3,
      "instrument": ""
    },
    {
      "id": "C1_CP_WHI_ACTIVE",
      "description": "",
      "start_date": "2000-09-08",
      "stop_date": "2024-09-30",
      "parameter_count": 1,
      "instrument": ""
    },
    {
      "id": "C1_CP_WHI_ELECTRON_DENSITY",
      "description": "",
      "start_date": "2001-02-02",
      "stop_date": "2024-09-30",
      "parameter_count": 1,
      "instrument": ""
    },
    {
      "id": "C1_CP_WHI_NATURAL",
      "description": "",
      "start_date": "2000-09-08",
      "stop_date": "2024-09-30",
      "parameter_count": 1,
      "instrument": ""
    },
    {
      "id": "C1_CP_WHI_PASSIVE_ACTIVE",
      "description": "",
      "start_date": "2000-09-08",
      "stop_date": "2024-09-30",
      "parameter_count": 1,
      "instrument": ""
    },
    {
      "id": "C1_CP_WHI_WAVE_FORM_ENERGY",
      "description": "",
      "start_date": "2000-09-08",
      "stop_date": "2024-09-30",
      "parameter_count": 1,
      "instrument": ""
    },
    {
      "id": "C1_JP_PMP",
      "description": "",
      "start_date": "2000-08-14",
      "stop_date": "2025-11-06",
      "parameter_count": 4,
      "instrument": ""
    },
    {
      "id": "C1_JP_PSE",
      "description": "",
      "start_date": "2000-08-01",
      "stop_date": "2025-11-05",
      "parameter_count": 5,
      "instrument": ""
    },
    {
      "id": "C1_PP_ASP",
      "description": "",
      "start_date": "2000-12-09",
      "stop_date": "2008-06-30",
      "parameter_count": 2,
      "instrument": ""
    },
    {
      "id": "C1_PP_CIS",
      "description": "",
      "start_date": "2000-12-09",
      "stop_date": "2022-09-30",
      "parameter_count": 12,
      "instrument": ""
    },
    {
      "id": "C1_PP_DWP",
      "description": "",
      "start_date": "2000-11-01",
      "stop_date": "2022-07-02",
      "parameter_count": 9,
      "instrument": ""
    },
    {
      "id": "C1_PP_EDI",
      "description": "",
      "start_date": "2001-02-01",
      "stop_date": "2024-09-29",
      "parameter_count": 3,
      "instrument": ""
    },
    {
      "id": "C1_PP_EFW",
      "description": "",
      "start_date": "2000-12-09",
      "stop_date": "2024-09-30",
      "parameter_count": 8,
      "instrument": ""
    },
    {
      "id": "C1_PP_PEA",
      "description": "",
      "start_date": "2000-11-01",
      "stop_date": "2023-12-31",
      "parameter_count": 6,
      "instrument": ""
    },
    {
      "id": "C1_PP_RAP",
      "description": "",
      "start_date": "2000-12-09",
      "stop_date": "2024-09-30",
      "parameter_count": 11,
      "instrument": ""
    },
    {
      "id": "C1_PP_STA",
      "description": "",
      "start_date": "2000-12-09",
      "stop_date": "2012-12-31",
      "parameter_count": 10,
      "instrument": ""
    },
    {
      "id": "C1_PP_WHI",
      "description": "",
      "start_date": "2000-12-10",
      "stop_date": "2012-12-31",
      "parameter_count": 8,
      "instrument": ""
    },
    {
      "id": "C1_UP_FGM",
      "description": "",
      "start_date": "2019-02-01",
      "stop_date": "2024-09-30",
      "parameter_count": 4,
      "instrument": ""
    },
    {
      "id": "C1_WAVEFORM_WBD",
      "description": "",
      "start_date": "2000-11-27",
      "stop_date": "2024-09-28",
      "parameter_count": 12,
      "instrument": ""
    },
    {
      "id": "C1_WAVEFORM_WBD_BM2",
      "description": "",
      "start_date": "2000-09-08",
      "stop_date": "2024-09-11",
      "parameter_count": 13,
      "instrument": ""
    },
    {
      "id": "C2_CP_EDI_AEDC",
      "description": "",
      "start_date": "2004-10-14",
      "stop_date": "2023-09-19",
      "parameter_count": 7,
      "instrument": ""
    },
    {
      "id": "C2_CP_EDI_MP",
      "description": "",
      "start_date": "2001-02-02",
      "stop_date": "2004-04-08",
      "parameter_count": 2,
      "instrument": ""
    },
    {
      "id": "C2_CP_EDI_QZC",
      "description": "",
      "start_date": "2001-02-02",
      "stop_date": "2005-06-04",
      "parameter_count": 2,
      "instrument": ""
    },
    {
      "id": "C2_CP_EDI_SPIN",
      "description": "",
      "start_date": "2001-02-02",
      "stop_date": "2010-01-01",
      "parameter_count": 2,
      "instrument": ""
    },
    {
      "id": "C2_CP_EFW_L3_E3D_INERT",
      "description": "",
      "start_date": "2000-12-02",
      "stop_date": "2022-08-23",
      "parameter_count": 3,
      "instrument": ""
    },
    {
      "id": "C2_CP_EFW_L3_P",
      "description": "",
      "start_date": "2000-12-01",
      "stop_date": "2024-07-16",
      "parameter_count": 1,
      "instrument": ""
    },
    {
      "id": "C2_CP_EFW_L3_V3D_INERT",
      "description": "",
      "start_date": "2000-12-02",
      "stop_date": "2022-08-23",
      "parameter_count": 3,
      "instrument": ""
    },
    {
      "id": "C2_CP_FGM_5VPS",
      "description": "",
      "start_date": "2000-12-02",
      "stop_date": "2024-09-08",
      "parameter_count": 3,
      "instrument": ""
    },
    {
      "id": "C2_CP_FGM_SPIN",
      "description": "",
      "start_date": "2001-01-30",
      "stop_date": "2024-09-08",
      "parameter_count": 3,
      "instrument": ""
    },
    {
      "id": "C2_CP_RAP_E3DD",
      "description": "",
      "start_date": "2000-12-16",
      "stop_date": "2024-01-31",
      "parameter_count": 2,
      "instrument": ""
    },
    {
      "id": "C2_CP_RAP_ESPCT6",
      "description": "",
      "start_date": "2000-12-07",
      "stop_date": "2024-02-01",
      "parameter_count": 2,
      "instrument": ""
    },
    {
      "id": "C2_CP_RAP_HSPCT",
      "description": "",
      "start_date": "2000-12-07",
      "stop_date": "2024-02-01",
      "parameter_count": 2,
      "instrument": ""
    },
    {
      "id": "C2_CP_RAP_I3DM_CNO",
      "description": "",
      "start_date": "2000-12-07",
      "stop_date": "2024-02-01",
      "parameter_count": 2,
      "instrument": ""
    },
    {
      "id": "C2_CP_RAP_I3DM_H",
      "description": "",
      "start_date": "2000-12-07",
      "stop_date": "2024-02-01",
      "parameter_count": 2,
      "instrument": ""
    },
    {
      "id": "C2_CP_RAP_I3DM_HE",
      "description": "",
      "start_date": "2000-12-07",
      "stop_date": "2024-02-01",
      "parameter_count": 2,
      "instrument": ""
    },
    {
      "id": "C2_CP_RAP_ISPCT_CNO",
      "description": "",
      "start_date": "2000-12-07",
      "stop_date": "2024-02-01",
      "parameter_count": 2,
      "instrument": ""
    },
    {
      "id": "C2_CP_RAP_ISPCT_HE",
      "description": "",
      "start_date": "2000-12-07",
      "stop_date": "2024-02-01",
      "parameter_count": 2,
      "instrument": ""
    },
    {
      "id": "C2_CP_RAP_L3DD",
      "description": "",
      "start_date": "2004-05-13",
      "stop_date": "2024-02-01",
      "parameter_count": 2,
      "instrument": ""
    },
    {
      "id": "C2_CP_RAP_PAD_E3DD",
      "description": "",
      "start_date": "2000-12-16",
      "stop_date": "2024-01-31",
      "parameter_count": 3,
      "instrument": ""
    },
    {
      "id": "C2_CP_RAP_PAD_H",
      "description": "",
      "start_date": "2000-12-07",
      "stop_date": "2024-02-01",
      "parameter_count": 3,
      "instrument": ""
    },
    {
      "id": "C2_CP_RAP_PAD_HE",
      "description": "",
      "start_date": "2000-12-07",
      "stop_date": "2024-02-01",
      "parameter_count": 3,
      "instrument": ""
    },
    {
      "id": "C2_CP_RAP_PAD_L3DD",
      "description": "",
      "start_date": "2004-05-13",
      "stop_date": "2024-02-01",
      "parameter_count": 3,
      "instrument": ""
    },
    {
      "id": "C2_CP_STA_CWF_GSE",
      "description": "",
      "start_date": "2000-09-05",
      "stop_date": "2024-07-16",
      "parameter_count": 1,
      "instrument": ""
    },
    {
      "id": "C2_CP_STA_PPP",
      "description": "",
      "start_date": "2000-12-02",
      "stop_date": "2024-07-16",
      "parameter_count": 7,
      "instrument": ""
    },
    {
      "id": "C2_CP_STA_PSD",
      "description": "",
      "start_date": "2000-09-05",
      "stop_date": "2024-07-16",
      "parameter_count": 2,
      "instrument": ""
    },
    {
      "id": "C2_CP_STA_SM",
      "description": "",
      "start_date": "2000-09-05",
      "stop_date": "2024-07-16",
      "parameter_count": 3,
      "instrument": ""
    },
    {
      "id": "C2_CP_WHI_ACTIVE",
      "description": "",
      "start_date": "2000-09-05",
      "stop_date": "2024-07-16",
      "parameter_count": 1,
      "instrument": ""
    },
    {
      "id": "C2_CP_WHI_ELECTRON_DENSITY",
      "description": "",
      "start_date": "2001-02-02",
      "stop_date": "2024-07-16",
      "parameter_count": 1,
      "instrument": ""
    },
    {
      "id": "C2_CP_WHI_NATURAL",
      "description": "",
      "start_date": "2000-09-05",
      "stop_date": "2024-07-16",
      "parameter_count": 1,
      "instrument": ""
    },
    {
      "id": "C2_CP_WHI_PASSIVE_ACTIVE",
      "description": "",
      "start_date": "2000-09-05",
      "stop_date": "2024-07-15",
      "parameter_count": 1,
      "instrument": ""
    },
    {
      "id": "C2_CP_WHI_WAVE_FORM_ENERGY",
      "description": "",
      "start_date": "2000-09-05",
      "stop_date": "2024-07-16",
      "parameter_count": 1,
      "instrument": ""
    },
    {
      "id": "C2_JP_PMP",
      "description": "",
      "start_date": "2000-08-14",
      "stop_date": "2024-09-08",
      "parameter_count": 4,
      "instrument": ""
    },
    {
      "id": "C2_JP_PSE",
      "description": "",
      "start_date": "2000-08-01",
      "stop_date": "2024-09-08",
      "parameter_count": 5,
      "instrument": ""
    },
    {
      "id": "C2_PP_ASP",
      "description": "",
      "start_date": "2000-12-09",
      "stop_date": "2008-06-30",
      "parameter_count": 2,
      "instrument": ""
    },
    {
      "id": "C2_PP_DWP",
      "description": "",
      "start_date": "2000-11-01",
      "stop_date": "2022-07-02",
      "parameter_count": 9,
      "instrument": ""
    },
    {
      "id": "C2_PP_EDI",
      "description": "",
      "start_date": "2001-02-01",
      "stop_date": "2024-09-09",
      "parameter_count": 4,
      "instrument": ""
    },
    {
      "id": "C2_PP_EFW",
      "description": "",
      "start_date": "2000-12-09",
      "stop_date": "2024-09-30",
      "parameter_count": 8,
      "instrument": ""
    },
    {
      "id": "C2_PP_PEA",
      "description": "",
      "start_date": "2000-11-01",
      "stop_date": "2023-12-31",
      "parameter_count": 6,
      "instrument": ""
    },
    {
      "id": "C2_PP_RAP",
      "description": "",
      "start_date": "2000-12-09",
      "stop_date": "2024-09-30",
      "parameter_count": 11,
      "instrument": ""
    },
    {
      "id": "C2_PP_STA",
      "description": "",
      "start_date": "2000-12-09",
      "stop_date": "2012-12-31",
      "parameter_count": 10,
      "instrument": ""
    },
    {
      "id": "C2_PP_WHI",
      "description": "",
      "start_date": "2000-12-10",
      "stop_date": "2012-12-31",
      "parameter_count": 8,
      "instrument": ""
    },
    {
      "id": "C2_UP_FGM",
      "description": "",
      "start_date": "2019-02-01",
      "stop_date": "2024-09-08",
      "parameter_count": 4,
      "instrument": ""
    },
    {
      "id": "C2_WAVEFORM_WBD",
      "description": "",
      "start_date": "2000-11-27",
      "stop_date": "2024-07-12",
      "parameter_count": 12,
      "instrument": ""
    },
    {
      "id": "C2_WAVEFORM_WBD_BM2",
      "description": "",
      "start_date": "2000-09-05",
      "stop_date": "2024-07-03",
      "parameter_count": 13,
      "instrument": ""
    },
    {
      "id": "C3_CP_CIS-CODIF_H1_1D_PEF",
      "description": "",
      "start_date": "2001-01-10",
      "stop_date": "2009-11-11",
      "parameter_count": 7,
      "instrument": ""
    },
    {
      "id": "C3_CP_CIS-CODIF_HE1_1D_PEF",
      "description": "",
      "start_date": "2001-01-10",
      "stop_date": "2009-11-11",
      "parameter_count": 7,
      "instrument": ""
    },
    {
      "id": "C3_CP_CIS-CODIF_HS_H1_PEF",
      "description": "",
      "start_date": "2001-01-10",
      "stop_date": "2009-11-11",
      "parameter_count": 6,
      "instrument": ""
    },
    {
      "id": "C3_CP_CIS-CODIF_HS_H1_PF",
      "description": "",
      "start_date": "2001-01-10",
      "stop_date": "2009-11-11",
      "parameter_count": 6,
      "instrument": ""
    },
    {
      "id": "C3_CP_CIS-CODIF_HS_H1_PSD",
      "description": "",
      "start_date": "2001-01-10",
      "stop_date": "2009-11-11",
      "parameter_count": 6,
      "instrument": ""
    },
    {
      "id": "C3_CP_CIS-CODIF_HS_HE1_PF",
      "description": "",
      "start_date": "2001-01-10",
      "stop_date": "2009-11-11",
      "parameter_count": 6,
      "instrument": ""
    },
    {
      "id": "C3_CP_CIS-CODIF_HS_HE1_PSD",
      "description": "",
      "start_date": "2001-01-10",
      "stop_date": "2009-11-11",
      "parameter_count": 6,
      "instrument": ""
    },
    {
      "id": "C3_CP_CIS-CODIF_HS_O1_PEF",
      "description": "",
      "start_date": "2001-01-10",
      "stop_date": "2009-11-11",
      "parameter_count": 6,
      "instrument": ""
    },
    {
      "id": "C3_CP_CIS-CODIF_HS_O1_PF",
      "description": "",
      "start_date": "2001-01-10",
      "stop_date": "2009-11-11",
      "parameter_count": 6,
      "instrument": ""
    },
    {
      "id": "C3_CP_CIS-CODIF_HS_O1_PSD",
      "description": "",
      "start_date": "2001-01-10",
      "stop_date": "2009-11-11",
      "parameter_count": 6,
      "instrument": ""
    },
    {
      "id": "C3_CP_CIS-CODIF_O1_1D_PEF",
      "description": "",
      "start_date": "2005-01-22",
      "stop_date": "2005-02-16",
      "parameter_count": 7,
      "instrument": ""
    },
    {
      "id": "C3_CP_CIS-CODIF_PAD_HS_H1_PF",
      "description": "",
      "start_date": "2001-01-31",
      "stop_date": "2009-11-11",
      "parameter_count": 4,
      "instrument": ""
    },
    {
      "id": "C3_CP_CIS-CODIF_PAD_HS_HE1_PF",
      "description": "",
      "start_date": "2001-01-31",
      "stop_date": "2009-11-11",
      "parameter_count": 4,
      "instrument": ""
    },
    {
      "id": "C3_CP_CIS-CODIF_PAD_HS_O1_PF",
      "description": "",
      "start_date": "2001-01-31",
      "stop_date": "2009-11-11",
      "parameter_count": 4,
      "instrument": ""
    },
    {
      "id": "C3_CP_CIS-HIA_HS_1D_PEF",
      "description": "",
      "start_date": "2001-01-10",
      "stop_date": "2009-11-11",
      "parameter_count": 7,
      "instrument": ""
    },
    {
      "id": "C3_CP_CIS-HIA_HS_MAG_IONS_PEF",
      "description": "",
      "start_date": "2001-01-10",
      "stop_date": "2009-11-11",
      "parameter_count": 6,
      "instrument": ""
    },
    {
      "id": "C3_CP_CIS-HIA_HS_MAG_IONS_PF",
      "description": "",
      "start_date": "2001-01-10",
      "stop_date": "2009-11-11",
      "parameter_count": 6,
      "instrument": ""
    },
    {
      "id": "C3_CP_CIS-HIA_HS_MAG_IONS_PSD",
      "description": "",
      "start_date": "2001-01-10",
      "stop_date": "2009-11-11",
      "parameter_count": 6,
      "instrument": ""
    },
    {
      "id": "C3_CP_CIS-HIA_HS_SW_IONS_PEF",
      "description": "",
      "start_date": "2001-01-12",
      "stop_date": "2009-06-01",
      "parameter_count": 6,
      "instrument": ""
    },
    {
      "id": "C3_CP_CIS-HIA_HS_SW_IONS_PF",
      "description": "",
      "start_date": "2001-01-12",
      "stop_date": "2009-06-01",
      "parameter_count": 6,
      "instrument": ""
    },
    {
      "id": "C3_CP_CIS-HIA_HS_SW_IONS_PSD",
      "description": "",
      "start_date": "2001-01-12",
      "stop_date": "2009-06-01",
      "parameter_count": 6,
      "instrument": ""
    },
    {
      "id": "C3_CP_CIS-HIA_LS_1D_PEF",
      "description": "",
      "start_date": "2001-01-12",
      "stop_date": "2009-06-01",
      "parameter_count": 7,
      "instrument": ""
    },
    {
      "id": "C3_CP_CIS-HIA_LS_SW_IONS_PEF",
      "description": "",
      "start_date": "2001-01-12",
      "stop_date": "2009-06-01",
      "parameter_count": 6,
      "instrument": ""
    },
    {
      "id": "C3_CP_CIS-HIA_LS_SW_IONS_PF",
      "description": "",
      "start_date": "2001-01-12",
      "stop_date": "2009-06-01",
      "parameter_count": 6,
      "instrument": ""
    },
    {
      "id": "C3_CP_CIS-HIA_LS_SW_IONS_PSD",
      "description": "",
      "start_date": "2001-01-12",
      "stop_date": "2009-06-01",
      "parameter_count": 6,
      "instrument": ""
    },
    {
      "id": "C3_CP_CIS-HIA_PAD_HS_MAG_IONS_PF",
      "description": "",
      "start_date": "2001-01-31",
      "stop_date": "2009-11-11",
      "parameter_count": 4,
      "instrument": ""
    },
    {
      "id": "C3_CP_EDI_AEDC",
      "description": "",
      "start_date": "2004-10-14",
      "stop_date": "2024-09-16",
      "parameter_count": 7,
      "instrument": ""
    },
    {
      "id": "C3_CP_EDI_MP",
      "description": "",
      "start_date": "2001-02-02",
      "stop_date": "2016-09-11",
      "parameter_count": 2,
      "instrument": ""
    },
    {
      "id": "C3_CP_EDI_QZC",
      "description": "",
      "start_date": "2001-02-02",
      "stop_date": "2024-09-15",
      "parameter_count": 2,
      "instrument": ""
    },
    {
      "id": "C3_CP_EDI_SPIN",
      "description": "",
      "start_date": "2001-02-02",
      "stop_date": "2024-09-15",
      "parameter_count": 2,
      "instrument": ""
    },
    {
      "id": "C3_CP_EFW_L3_E3D_INERT",
      "description": "",
      "start_date": "2000-12-02",
      "stop_date": "2014-11-03",
      "parameter_count": 3,
      "instrument": ""
    },
    {
      "id": "C3_CP_EFW_L3_P",
      "description": "",
      "start_date": "2000-12-01",
      "stop_date": "2024-06-30",
      "parameter_count": 1,
      "instrument": ""
    },
    {
      "id": "C3_CP_EFW_L3_V3D_INERT",
      "description": "",
      "start_date": "2000-12-02",
      "stop_date": "2014-11-03",
      "parameter_count": 3,
      "instrument": ""
    },
    {
      "id": "C3_CP_FGM_5VPS",
      "description": "",
      "start_date": "2000-12-02",
      "stop_date": "2024-09-29",
      "parameter_count": 3,
      "instrument": ""
    },
    {
      "id": "C3_CP_FGM_SPIN",
      "description": "",
      "start_date": "2001-01-30",
      "stop_date": "2024-09-29",
      "parameter_count": 3,
      "instrument": ""
    },
    {
      "id": "C3_CP_RAP_E3DD",
      "description": "",
      "start_date": "2000-12-07",
      "stop_date": "2024-09-29",
      "parameter_count": 2,
      "instrument": ""
    },
    {
      "id": "C3_CP_RAP_ESPCT6",
      "description": "",
      "start_date": "2000-12-05",
      "stop_date": "2024-09-30",
      "parameter_count": 2,
      "instrument": ""
    },
    {
      "id": "C3_CP_RAP_HSPCT",
      "description": "",
      "start_date": "2000-12-07",
      "stop_date": "2009-11-29",
      "parameter_count": 2,
      "instrument": ""
    },
    {
      "id": "C3_CP_RAP_I3DM_CNO",
      "description": "",
      "start_date": "2000-12-07",
      "stop_date": "2009-11-29",
      "parameter_count": 2,
      "instrument": ""
    },
    {
      "id": "C3_CP_RAP_I3DM_H",
      "description": "",
      "start_date": "2000-12-07",
      "stop_date": "2009-11-29",
      "parameter_count": 2,
      "instrument": ""
    },
    {
      "id": "C3_CP_RAP_I3DM_HE",
      "description": "",
      "start_date": "2000-12-07",
      "stop_date": "2009-11-29",
      "parameter_count": 2,
      "instrument": ""
    },
    {
      "id": "C3_CP_RAP_ISPCT_CNO",
      "description": "",
      "start_date": "2000-12-07",
      "stop_date": "2009-11-29",
      "parameter_count": 2,
      "instrument": ""
    },
    {
      "id": "C3_CP_RAP_ISPCT_HE",
      "description": "",
      "start_date": "2000-12-07",
      "stop_date": "2009-11-29",
      "parameter_count": 2,
      "instrument": ""
    },
    {
      "id": "C3_CP_RAP_L3DD",
      "description": "",
      "start_date": "2004-04-30",
      "stop_date": "2024-09-30",
      "parameter_count": 2,
      "instrument": ""
    },
    {
      "id": "C3_CP_RAP_PAD_CNO",
      "description": "",
      "start_date": "2000-12-07",
      "stop_date": "2009-11-30",
      "parameter_count": 3,
      "instrument": ""
    },
    {
      "id": "C3_CP_RAP_PAD_E3DD",
      "description": "",
      "start_date": "2000-12-07",
      "stop_date": "2024-09-28",
      "parameter_count": 3,
      "instrument": ""
    },
    {
      "id": "C3_CP_RAP_PAD_H",
      "description": "",
      "start_date": "2000-12-07",
      "stop_date": "2009-11-30",
      "parameter_count": 3,
      "instrument": ""
    },
    {
      "id": "C3_CP_RAP_PAD_HE",
      "description": "",
      "start_date": "2000-12-07",
      "stop_date": "2009-11-30",
      "parameter_count": 3,
      "instrument": ""
    },
    {
      "id": "C3_CP_RAP_PAD_L3DD",
      "description": "",
      "start_date": "2004-04-30",
      "stop_date": "2024-09-29",
      "parameter_count": 3,
      "instrument": ""
    },
    {
      "id": "C3_CP_STA_CWF_GSE",
      "description": "",
      "start_date": "2000-10-09",
      "stop_date": "2024-09-30",
      "parameter_count": 1,
      "instrument": ""
    },
    {
      "id": "C3_CP_STA_PPP",
      "description": "",
      "start_date": "2000-12-07",
      "stop_date": "2024-09-29",
      "parameter_count": 7,
      "instrument": ""
    },
    {
      "id": "C3_CP_STA_PSD",
      "description": "",
      "start_date": "2000-10-09",
      "stop_date": "2024-09-30",
      "parameter_count": 2,
      "instrument": ""
    },
    {
      "id": "C3_CP_STA_SM",
      "description": "",
      "start_date": "2000-10-09",
      "stop_date": "2024-09-30",
      "parameter_count": 3,
      "instrument": ""
    },
    {
      "id": "C3_CP_WHI_ACTIVE",
      "description": "",
      "start_date": "2000-10-11",
      "stop_date": "2024-09-30",
      "parameter_count": 1,
      "instrument": ""
    },
    {
      "id": "C3_CP_WHI_ELECTRON_DENSITY",
      "description": "",
      "start_date": "2001-02-02",
      "stop_date": "2024-09-30",
      "parameter_count": 1,
      "instrument": ""
    },
    {
      "id": "C3_CP_WHI_NATURAL",
      "description": "",
      "start_date": "2000-10-11",
      "stop_date": "2024-09-30",
      "parameter_count": 1,
      "instrument": ""
    },
    {
      "id": "C3_CP_WHI_PASSIVE_ACTIVE",
      "description": "",
      "start_date": "2000-10-11",
      "stop_date": "2024-09-30",
      "parameter_count": 1,
      "instrument": ""
    },
    {
      "id": "C3_CP_WHI_WAVE_FORM_ENERGY",
      "description": "",
      "start_date": "2000-10-11",
      "stop_date": "2024-09-30",
      "parameter_count": 1,
      "instrument": ""
    },
    {
      "id": "C3_JP_PMP",
      "description": "",
      "start_date": "2000-08-14",
      "stop_date": "2025-11-30",
      "parameter_count": 4,
      "instrument": ""
    },
    {
      "id": "C3_JP_PSE",
      "description": "",
      "start_date": "2000-08-01",
      "stop_date": "2025-11-30",
      "parameter_count": 5,
      "instrument": ""
    },
    {
      "id": "C3_PP_ASP",
      "description": "",
      "start_date": "2000-12-09",
      "stop_date": "2008-06-30",
      "parameter_count": 2,
      "instrument": ""
    },
    {
      "id": "C3_PP_CIS",
      "description": "",
      "start_date": "2000-12-09",
      "stop_date": "2021-12-31",
      "parameter_count": 12,
      "instrument": ""
    },
    {
      "id": "C3_PP_EDI",
      "description": "",
      "start_date": "2001-02-01",
      "stop_date": "2024-09-29",
      "parameter_count": 4,
      "instrument": ""
    },
    {
      "id": "C3_PP_EFW",
      "description": "",
      "start_date": "2000-12-09",
      "stop_date": "2024-09-30",
      "parameter_count": 8,
      "instrument": ""
    },
    {
      "id": "C3_PP_PEA",
      "description": "",
      "start_date": "2000-11-01",
      "stop_date": "2023-12-31",
      "parameter_count": 6,
      "instrument": ""
    },
    {
      "id": "C3_PP_RAP",
      "description": "",
      "start_date": "2000-12-09",
      "stop_date": "2024-09-30",
      "parameter_count": 11,
      "instrument": ""
    },
    {
      "id": "C3_PP_STA",
      "description": "",
      "start_date": "2000-12-09",
      "stop_date": "2012-12-31",
      "parameter_count": 10,
      "instrument": ""
    },
    {
      "id": "C3_PP_WHI",
      "description": "",
      "start_date": "2000-12-10",
      "stop_date": "2012-12-31",
      "parameter_count": 8,
      "instrument": ""
    },
    {
      "id": "C3_UP_FGM",
      "description": "",
      "start_date": "2019-02-01",
      "stop_date": "2024-09-30",
      "parameter_count": 4,
      "instrument": ""
    },
    {
      "id": "C3_WAVEFORM_WBD",
      "description": "",
      "start_date": "2000-11-27",
      "stop_date": "2024-09-29",
      "parameter_count": 12,
      "instrument": ""
    },
    {
      "id": "C3_WAVEFORM_WBD_BM2",
      "description": "",
      "start_date": "2000-10-12",
      "stop_date": "2024-09-11",
      "parameter_count": 13,
      "instrument": ""
    },
    {
      "id": "C4_CP_CIS-CODIF_H1_1D_PEF",
      "description": "",
      "start_date": "2001-01-09",
      "stop_date": "2024-09-30",
      "parameter_count": 7,
      "instrument": ""
    },
    {
      "id": "C4_CP_CIS-CODIF_HE1_1D_PEF",
      "description": "",
      "start_date": "2001-01-09",
      "stop_date": "2024-09-30",
      "parameter_count": 7,
      "instrument": ""
    },
    {
      "id": "C4_CP_CIS-CODIF_HE1_DENSITY_CORRECTED",
      "description": "",
      "start_date": "2001-03-01",
      "stop_date": "2007-12-30",
      "parameter_count": 3,
      "instrument": ""
    },
    {
      "id": "C4_CP_CIS-CODIF_HS_H1_PEF",
      "description": "",
      "start_date": "2001-01-09",
      "stop_date": "2024-09-30",
      "parameter_count": 6,
      "instrument": ""
    },
    {
      "id": "C4_CP_CIS-CODIF_HS_H1_PF",
      "description": "",
      "start_date": "2001-01-09",
      "stop_date": "2024-09-30",
      "parameter_count": 6,
      "instrument": ""
    },
    {
      "id": "C4_CP_CIS-CODIF_HS_H1_PSD",
      "description": "",
      "start_date": "2001-01-09",
      "stop_date": "2024-09-30",
      "parameter_count": 6,
      "instrument": ""
    },
    {
      "id": "C4_CP_CIS-CODIF_HS_HE1_PF",
      "description": "",
      "start_date": "2001-01-09",
      "stop_date": "2024-09-30",
      "parameter_count": 6,
      "instrument": ""
    },
    {
      "id": "C4_CP_CIS-CODIF_HS_HE1_PSD",
      "description": "",
      "start_date": "2001-01-09",
      "stop_date": "2024-09-30",
      "parameter_count": 6,
      "instrument": ""
    },
    {
      "id": "C4_CP_CIS-CODIF_HS_O1_PEF",
      "description": "",
      "start_date": "2001-01-09",
      "stop_date": "2024-09-30",
      "parameter_count": 6,
      "instrument": ""
    },
    {
      "id": "C4_CP_CIS-CODIF_HS_O1_PF",
      "description": "",
      "start_date": "2001-01-09",
      "stop_date": "2024-09-30",
      "parameter_count": 6,
      "instrument": ""
    },
    {
      "id": "C4_CP_CIS-CODIF_HS_O1_PSD",
      "description": "",
      "start_date": "2001-01-09",
      "stop_date": "2024-09-30",
      "parameter_count": 6,
      "instrument": ""
    },
    {
      "id": "C4_CP_CIS-CODIF_LS_H1_PEF",
      "description": "",
      "start_date": "2001-01-09",
      "stop_date": "2024-08-19",
      "parameter_count": 6,
      "instrument": ""
    },
    {
      "id": "C4_CP_CIS-CODIF_LS_H1_PF",
      "description": "",
      "start_date": "2001-01-09",
      "stop_date": "2024-08-19",
      "parameter_count": 6,
      "instrument": ""
    },
    {
      "id": "C4_CP_CIS-CODIF_LS_H1_PSD",
      "description": "",
      "start_date": "2001-01-09",
      "stop_date": "2024-08-19",
      "parameter_count": 6,
      "instrument": ""
    },
    {
      "id": "C4_CP_CIS-CODIF_LS_HE1_PEF",
      "description": "",
      "start_date": "2001-01-09",
      "stop_date": "2024-08-19",
      "parameter_count": 6,
      "instrument": ""
    },
    {
      "id": "C4_CP_CIS-CODIF_LS_HE1_PF",
      "description": "",
      "start_date": "2001-01-09",
      "stop_date": "2024-08-19",
      "parameter_count": 6,
      "instrument": ""
    },
    {
      "id": "C4_CP_CIS-CODIF_LS_O1_PEF",
      "description": "",
      "start_date": "2001-01-09",
      "stop_date": "2024-08-19",
      "parameter_count": 6,
      "instrument": ""
    },
    {
      "id": "C4_CP_CIS-CODIF_LS_O1_PF",
      "description": "",
      "start_date": "2001-01-09",
      "stop_date": "2024-08-19",
      "parameter_count": 6,
      "instrument": ""
    },
    {
      "id": "C4_CP_CIS-CODIF_LS_O1_PSD",
      "description": "",
      "start_date": "2001-01-09",
      "stop_date": "2024-08-19",
      "parameter_count": 6,
      "instrument": ""
    },
    {
      "id": "C4_CP_CIS-CODIF_O1_1D_PEF",
      "description": "",
      "start_date": "2004-05-07",
      "stop_date": "2004-06-01",
      "parameter_count": 7,
      "instrument": ""
    },
    {
      "id": "C4_CP_CIS-CODIF_PAD_HS_H1_PF",
      "description": "",
      "start_date": "2001-01-31",
      "stop_date": "2024-09-29",
      "parameter_count": 4,
      "instrument": ""
    },
    {
      "id": "C4_CP_CIS-CODIF_PAD_HS_HE1_PF",
      "description": "",
      "start_date": "2001-01-31",
      "stop_date": "2024-09-29",
      "parameter_count": 4,
      "instrument": ""
    },
    {
      "id": "C4_CP_CIS-CODIF_PAD_HS_O1_PF",
      "description": "",
      "start_date": "2001-01-31",
      "stop_date": "2024-09-29",
      "parameter_count": 4,
      "instrument": ""
    },
    {
      "id": "C4_CP_CIS-CODIF_PAD_LS_H1_PF",
      "description": "",
      "start_date": "2001-01-31",
      "stop_date": "2024-08-19",
      "parameter_count": 4,
      "instrument": ""
    },
    {
      "id": "C4_CP_CIS-CODIF_PAD_LS_HE1_PF",
      "description": "",
      "start_date": "2001-01-31",
      "stop_date": "2024-08-19",
      "parameter_count": 4,
      "instrument": ""
    },
    {
      "id": "C4_CP_CIS-CODIF_PAD_LS_O1_PF",
      "description": "",
      "start_date": "2001-01-31",
      "stop_date": "2024-08-19",
      "parameter_count": 4,
      "instrument": ""
    },
    {
      "id": "C4_CP_EFW_L3_E3D_INERT",
      "description": "",
      "start_date": "2001-01-07",
      "stop_date": "2024-09-29",
      "parameter_count": 3,
      "instrument": ""
    },
    {
      "id": "C4_CP_EFW_L3_P",
      "description": "",
      "start_date": "2000-12-01",
      "stop_date": "2024-09-30",
      "parameter_count": 1,
      "instrument": ""
    },
    {
      "id": "C4_CP_EFW_L3_V3D_INERT",
      "description": "",
      "start_date": "2001-01-07",
      "stop_date": "2024-09-29",
      "parameter_count": 3,
      "instrument": ""
    },
    {
      "id": "C4_CP_FGM_5VPS",
      "description": "",
      "start_date": "2001-01-07",
      "stop_date": "2024-09-16",
      "parameter_count": 3,
      "instrument": ""
    },
    {
      "id": "C4_CP_FGM_SPIN",
      "description": "",
      "start_date": "2001-01-31",
      "stop_date": "2024-09-29",
      "parameter_count": 3,
      "instrument": ""
    },
    {
      "id": "C4_CP_RAP_E3DD",
      "description": "",
      "start_date": "2000-12-11",
      "stop_date": "2024-09-29",
      "parameter_count": 2,
      "instrument": ""
    },
    {
      "id": "C4_CP_RAP_ESPCT6",
      "description": "",
      "start_date": "2000-12-05",
      "stop_date": "2024-09-30",
      "parameter_count": 2,
      "instrument": ""
    },
    {
      "id": "C4_CP_RAP_HSPCT",
      "description": "",
      "start_date": "2000-12-07",
      "stop_date": "2024-09-30",
      "parameter_count": 2,
      "instrument": ""
    },
    {
      "id": "C4_CP_RAP_I3DM_CNO",
      "description": "",
      "start_date": "2000-12-07",
      "stop_date": "2024-09-30",
      "parameter_count": 2,
      "instrument": ""
    },
    {
      "id": "C4_CP_RAP_I3DM_H",
      "description": "",
      "start_date": "2000-12-07",
      "stop_date": "2024-09-30",
      "parameter_count": 2,
      "instrument": ""
    },
    {
      "id": "C4_CP_RAP_I3DM_HE",
      "description": "",
      "start_date": "2000-12-07",
      "stop_date": "2024-09-30",
      "parameter_count": 2,
      "instrument": ""
    },
    {
      "id": "C4_CP_RAP_ISPCT_CNO",
      "description": "",
      "start_date": "2000-12-07",
      "stop_date": "2024-09-30",
      "parameter_count": 2,
      "instrument": ""
    },
    {
      "id": "C4_CP_RAP_ISPCT_HE",
      "description": "",
      "start_date": "2000-12-07",
      "stop_date": "2024-09-30",
      "parameter_count": 2,
      "instrument": ""
    },
    {
      "id": "C4_CP_RAP_L3DD",
      "description": "",
      "start_date": "2004-05-03",
      "stop_date": "2024-09-30",
      "parameter_count": 2,
      "instrument": ""
    },
    {
      "id": "C4_CP_RAP_PAD_CNO",
      "description": "",
      "start_date": "2001-01-09",
      "stop_date": "2024-09-29",
      "parameter_count": 3,
      "instrument": ""
    },
    {
      "id": "C4_CP_RAP_PAD_E3DD",
      "description": "",
      "start_date": "2001-01-12",
      "stop_date": "2024-09-28",
      "parameter_count": 3,
      "instrument": ""
    },
    {
      "id": "C4_CP_RAP_PAD_H",
      "description": "",
      "start_date": "2001-01-09",
      "stop_date": "2024-09-29",
      "parameter_count": 3,
      "instrument": ""
    },
    {
      "id": "C4_CP_RAP_PAD_HE",
      "description": "",
      "start_date": "2001-01-09",
      "stop_date": "2024-09-29",
      "parameter_count": 3,
      "instrument": ""
    },
    {
      "id": "C4_CP_RAP_PAD_L3DD",
      "description": "",
      "start_date": "2004-05-03",
      "stop_date": "2024-09-29",
      "parameter_count": 3,
      "instrument": ""
    },
    {
      "id": "C4_CP_STA_CWF_GSE",
      "description": "",
      "start_date": "2000-10-23",
      "stop_date": "2024-09-30",
      "parameter_count": 1,
      "instrument": ""
    },
    {
      "id": "C4_CP_STA_PPP",
      "description": "",
      "start_date": "2001-01-07",
      "stop_date": "2024-09-29",
      "parameter_count": 7,
      "instrument": ""
    },
    {
      "id": "C4_CP_STA_PSD",
      "description": "",
      "start_date": "2000-10-23",
      "stop_date": "2024-09-30",
      "parameter_count": 2,
      "instrument": ""
    },
    {
      "id": "C4_CP_STA_SM",
      "description": "",
      "start_date": "2000-10-23",
      "stop_date": "2024-09-30",
      "parameter_count": 3,
      "instrument": ""
    },
    {
      "id": "C4_CP_WHI_ACTIVE",
      "description": "",
      "start_date": "2000-10-25",
      "stop_date": "2024-09-30",
      "parameter_count": 1,
      "instrument": ""
    },
    {
      "id": "C4_CP_WHI_ELECTRON_DENSITY",
      "description": "",
      "start_date": "2001-02-02",
      "stop_date": "2024-09-30",
      "parameter_count": 1,
      "instrument": ""
    },
    {
      "id": "C4_CP_WHI_NATURAL",
      "description": "",
      "start_date": "2000-10-25",
      "stop_date": "2024-09-30",
      "parameter_count": 1,
      "instrument": ""
    },
    {
      "id": "C4_CP_WHI_PASSIVE_ACTIVE",
      "description": "",
      "start_date": "2000-10-25",
      "stop_date": "2024-09-30",
      "parameter_count": 1,
      "instrument": ""
    },
    {
      "id": "C4_CP_WHI_WAVE_FORM_ENERGY",
      "description": "",
      "start_date": "2000-10-25",
      "stop_date": "2024-09-30",
      "parameter_count": 1,
      "instrument": ""
    },
    {
      "id": "C4_JP_PMP",
      "description": "",
      "start_date": "2000-08-14",
      "stop_date": "2025-11-30",
      "parameter_count": 4,
      "instrument": ""
    },
    {
      "id": "C4_JP_PSE",
      "description": "",
      "start_date": "2000-08-01",
      "stop_date": "2025-11-30",
      "parameter_count": 5,
      "instrument": ""
    },
    {
      "id": "C4_PP_ASP",
      "description": "",
      "start_date": "2000-12-09",
      "stop_date": "2008-06-30",
      "parameter_count": 2,
      "instrument": ""
    },
    {
      "id": "C4_PP_CIS",
      "description": "",
      "start_date": "2000-12-09",
      "stop_date": "2024-09-30",
      "parameter_count": 12,
      "instrument": ""
    },
    {
      "id": "C4_PP_DWP",
      "description": "",
      "start_date": "2000-11-01",
      "stop_date": "2022-07-01",
      "parameter_count": 9,
      "instrument": ""
    },
    {
      "id": "C4_PP_EDI",
      "description": "",
      "start_date": "2001-02-01",
      "stop_date": "2024-09-29",
      "parameter_count": 3,
      "instrument": ""
    },
    {
      "id": "C4_PP_EFW",
      "description": "",
      "start_date": "2000-12-09",
      "stop_date": "2024-09-30",
      "parameter_count": 8,
      "instrument": ""
    },
    {
      "id": "C4_PP_PEA",
      "description": "",
      "start_date": "2000-11-01",
      "stop_date": "2023-12-31",
      "parameter_count": 6,
      "instrument": ""
    },
    {
      "id": "C4_PP_RAP",
      "description": "",
      "start_date": "2000-12-09",
      "stop_date": "2024-09-30",
      "parameter_count": 11,
      "instrument": ""
    },
    {
      "id": "C4_PP_STA",
      "description": "",
      "start_date": "2000-12-09",
      "stop_date": "2012-12-31",
      "parameter_count": 10,
      "instrument": ""
    },
    {
      "id": "C4_PP_WHI",
      "description": "",
      "start_date": "2000-12-10",
      "stop_date": "2012-12-31",
      "parameter_count": 8,
      "instrument": ""
    },
    {
      "id": "C4_UP_FGM",
      "description": "",
      "start_date": "2019-02-01",
      "stop_date": "2024-09-30",
      "parameter_count": 4,
      "instrument": ""
    },
    {
      "id": "C4_WAVEFORM_WBD",
      "description": "",
      "start_date": "2001-01-04",
      "stop_date": "2024-09-29",
      "parameter_count": 12,
      "instrument": ""
    },
    {
      "id": "C4_WAVEFORM_WBD_BM2",
      "description": "",
      "start_date": "2000-10-25",
      "stop_date": "2024-09-11",
      "parameter_count": 13,
      "instrument": ""
    },
    {
      "id": "CL_JP_PCY",
      "description": "",
      "start_date": "1999-01-01",
      "stop_date": "2024-12-01",
      "parameter_count": 5,
      "instrument": ""
    },
    {
      "id": "CL_JP_PGP",
      "description": "",
      "start_date": "2000-08-14",
      "stop_date": "2025-11-30",
      "parameter_count": 16,
      "instrument": ""
    },
    {
      "id": "CL_OR_GIFWALK",
      "description": "",
      "start_date": "2004-08-09",
      "stop_date": "2004-08-09",
      "parameter_count": 0,
      "instrument": ""
    },
    {
      "id": "CL_SP_AUX",
      "description": "",
      "start_date": "2000-08-22",
      "stop_date": "2024-09-30",
      "parameter_count": 31,
      "instrument": ""
    }
  ]
}
