{
  "mission_id": "IMAGE",
  "dataset_count": 20,
  "generated_at": "2026-02-19T10:20:14Z",
  "datasets": [
    {
      "id": "IMAGE_M2_EUV",
      "description": "",
      "start_date": "2000-05-03",
      "stop_date": "2005-12-17",
      "parameter_count": 10,
      "instrument": ""
    },
    {
      "id": "IM_ELECTRON_DENSITY_RPI",
      "description": "",
      "start_date": "2001-01-01",
      "stop_date": "2005-12-18",
      "parameter_count": 15,
      "instrument": ""
    },
    {
      "id": "IM_HK_ADS",
      "description": "",
      "start_date": "2000-03-25",
      "stop_date": "2005-12-18",
      "parameter_count": 45,
      "instrument": ""
    },
    {
      "id": "IM_HK_AST",
      "description": "",
      "start_date": "2000-03-25",
      "stop_date": "2005-12-18",
      "parameter_count": 34,
      "instrument": ""
    },
    {
      "id": "IM_HK_COM",
      "description": "",
      "start_date": "2000-03-25",
      "stop_date": "2005-12-18",
      "parameter_count": 16,
      "instrument": ""
    },
    {
      "id": "IM_HK_FSW",
      "description": "",
      "start_date": "2000-03-25",
      "stop_date": "2005-12-18",
      "parameter_count": 47,
      "instrument": ""
    },
    {
      "id": "IM_HK_PWR",
      "description": "",
      "start_date": "2000-03-25",
      "stop_date": "2005-12-18",
      "parameter_count": 25,
      "instrument": ""
    },
    {
      "id": "IM_HK_TML",
      "description": "",
      "start_date": "2000-03-25",
      "stop_date": "2005-12-18",
      "parameter_count": 28,
      "instrument": ""
    },
    {
      "id": "IM_K0_EUV",
      "description": "",
      "start_date": "2000-03-28",
      "stop_date": "2005-12-18",
      "parameter_count": 13,
      "instrument": ""
    },
    {
      "id": "IM_K0_HENA",
      "description": "",
      "start_date": "2000-04-21",
      "stop_date": "2005-12-18",
      "parameter_count": 34,
      "instrument": ""
    },
    {
      "id": "IM_K0_LENA",
      "description": "",
      "start_date": "2000-05-24",
      "stop_date": "2005-12-18",
      "parameter_count": 19,
      "instrument": ""
    },
    {
      "id": "IM_K0_MENA",
      "description": "",
      "start_date": "2000-04-04",
      "stop_date": "2005-12-18",
      "parameter_count": 29,
      "instrument": ""
    },
    {
      "id": "IM_K0_RPI",
      "description": "",
      "start_date": "2000-03-26",
      "stop_date": "2005-12-18",
      "parameter_count": 18,
      "instrument": ""
    },
    {
      "id": "IM_K0_SIE",
      "description": "",
      "start_date": "2000-04-25",
      "stop_date": "2005-12-18",
      "parameter_count": 29,
      "instrument": ""
    },
    {
      "id": "IM_K0_SIP",
      "description": "",
      "start_date": "2000-04-25",
      "stop_date": "2005-12-18",
      "parameter_count": 31,
      "instrument": ""
    },
    {
      "id": "IM_K0_WIC",
      "description": "",
      "start_date": "2000-04-25",
      "stop_date": "2005-12-18",
      "parameter_count": 33,
      "instrument": ""
    },
    {
      "id": "IM_K1_RPI",
      "description": "",
      "start_date": "2000-04-12",
      "stop_date": "2005-12-18",
      "parameter_count": 7,
      "instrument": ""
    },
    {
      "id": "IM_OR_DEF",
      "description": "",
      "start_date": "2000-03-27",
      "stop_date": "2005-12-19",
      "parameter_count": 11,
      "instrument": ""
    },
    {
      "id": "IM_OR_GIFWALK",
      "description": "",
      "start_date": "2004-08-09",
      "stop_date": "2004-08-09",
      "parameter_count": 0,
      "instrument": ""
    },
    {
      "id": "IM_OR_PRE",
      "description": "",
      "start_date": "2001-02-21",
      "stop_date": "2006-01-30",
      "parameter_count": 11,
      "instrument": ""
    }
  ]
}
